{
	"common": {
		"name": "ems",
		"version": "0.0.3",
		"news": {
			"0.0.3": {
				"en": "Disable custom admin UI until admin/ exists (fixes 404 index.html)",
				"de": "Admin-UI aus bis admin/ vorhanden (behebt 404 index.html)"
			},
			"0.0.2": {
				"en": "Ship prebuilt build/ — fixes ioBroker install without tsconfig in npm pack",
				"de": "Vorkompiliertes build/ — Install auf ioBroker ohne postinstall-Build"
			},
			"0.0.1": {
				"en": "Initial: ems.0 states, command inbox, dryrun-only pipeline",
				"de": "Erstversion: ems.0 States, Befehlseingang, nur Dryrun"
			}
		},
		"title": {
			"en": "EMS V2",
			"de": "EMS V2"
		},
		"desc": {
			"en": "Execution gateway for EMS V2. v0.0.1: dryrun + audit only, no device writes.",
			"de": "Ausführungs-Gateway für EMS V2. v0.0.1: nur Dryrun + Audit, keine Geräte-Writes."
		},
		"authors": ["weindler"],
		"license": "MIT",
		"platform": "All",
		"mode": "daemon",
		"type": "adapter",
		"category": "energy",
		"connectionType": "local",
		"dataSource": "poll",
		"enabled": true,
		"compact": true,
		"dependencies": [
			{
				"js-controller": ">=5.0.19"
			}
		],
		"adminUI": {
			"enabled": false
		}
	},
	"native": {},
	"objects": [],
	"instanceObjects": []
}
